mcterm.py
mcterm-0.9.7.dist-info/LICENSE
mcterm-0.9.7.dist-info/METADATA
mcterm-0.9.7.dist-info/WHEEL
mcterm-0.9.7.dist-info/entry_points.txt
mcterm-0.9.7.dist-info/top_level.txt
mcterm-0.9.7.dist-info/RECORD
