Metadata-Version: 2.1
Name: mcterm
Version: 0.9.7
Summary: Better Minecraft Server Terminal
Home-page: https://newgit.inuxnet.org/devel/bettermcrcon
Author: Jess Williams
Author-email: Jess Williams <devel@inuxnet.org>
License: MIT License
Project-URL: Homepage, https://newgit.inuxnet.org/devel/bettermcrcon
Project-URL: Documentation, https://newgit.inuxnet.org/devel/bettermcrcon
Project-URL: Repository, https://newgit.inuxnet.org/devel/bettermcrcon
Keywords: minecraft,mcrcon,rcon,remote,command,mojang,cli,mcterm,terminal
Classifier: Intended Audience :: Developers
Classifier: Intended Audience :: System Administrators
Classifier: License :: OSI Approved :: MIT License
Classifier: Programming Language :: Python :: 3
Classifier: Operating System :: OS Independent
Requires-Python: >=3.8
License-File: LICENSE
Requires-Dist: mcrcon>=0.6.0
Requires-Dist: prompt-toolkit>=3.0.0
Requires-Dist: requests>=1.0.0
